.DS_Store
qbism/.DS_Store
qbism/__init__.py
qbism/_nbdev.py
qbism/kraus.py
qbism/povm.py
qbism/random.py
qbism/rics.py
qbism/sics.py
qbism/weyl_heisenberg.py
qbism/sic_povms/.DS_Store
qbism/sic_povms/d10.txt
qbism/sic_povms/d100.txt
qbism/sic_povms/d101.txt
qbism/sic_povms/d102.txt
qbism/sic_povms/d103.txt
qbism/sic_povms/d104.txt
qbism/sic_povms/d105.txt
qbism/sic_povms/d106.txt
qbism/sic_povms/d107.txt
qbism/sic_povms/d108.txt
qbism/sic_povms/d109.txt
qbism/sic_povms/d11.txt
qbism/sic_povms/d110.txt
qbism/sic_povms/d111.txt
qbism/sic_povms/d112.txt
qbism/sic_povms/d113.txt
qbism/sic_povms/d114.txt
qbism/sic_povms/d115.txt
qbism/sic_povms/d116.txt
qbism/sic_povms/d117.txt
qbism/sic_povms/d118.txt
qbism/sic_povms/d119.txt
qbism/sic_povms/d12.txt
qbism/sic_povms/d120.txt
qbism/sic_povms/d121.txt
qbism/sic_povms/d122.txt
qbism/sic_povms/d123.txt
qbism/sic_povms/d124.txt
qbism/sic_povms/d125.txt
qbism/sic_povms/d126.txt
qbism/sic_povms/d127.txt
qbism/sic_povms/d128.txt
qbism/sic_povms/d129.txt
qbism/sic_povms/d13.txt
qbism/sic_povms/d130.txt
qbism/sic_povms/d131.txt
qbism/sic_povms/d132.txt
qbism/sic_povms/d133.txt
qbism/sic_povms/d134.txt
qbism/sic_povms/d135.txt
qbism/sic_povms/d136.txt
qbism/sic_povms/d137.txt
qbism/sic_povms/d138.txt
qbism/sic_povms/d139.txt
qbism/sic_povms/d14.txt
qbism/sic_povms/d140.txt
qbism/sic_povms/d141.txt
qbism/sic_povms/d142.txt
qbism/sic_povms/d143.txt
qbism/sic_povms/d144.txt
qbism/sic_povms/d145.txt
qbism/sic_povms/d146.txt
qbism/sic_povms/d147.txt
qbism/sic_povms/d148.txt
qbism/sic_povms/d149.txt
qbism/sic_povms/d15.txt
qbism/sic_povms/d150.txt
qbism/sic_povms/d151.txt
qbism/sic_povms/d16.txt
qbism/sic_povms/d17.txt
qbism/sic_povms/d18.txt
qbism/sic_povms/d19.txt
qbism/sic_povms/d2.txt
qbism/sic_povms/d20.txt
qbism/sic_povms/d21.txt
qbism/sic_povms/d22.txt
qbism/sic_povms/d23.txt
qbism/sic_povms/d24.txt
qbism/sic_povms/d25.txt
qbism/sic_povms/d26.txt
qbism/sic_povms/d27.txt
qbism/sic_povms/d28.txt
qbism/sic_povms/d29.txt
qbism-0.1.0.6.dist-info/LICENSE
qbism-0.1.0.6.dist-info/METADATA
qbism-0.1.0.6.dist-info/WHEEL
qbism-0.1.0.6.dist-info/entry_points.txt
qbism-0.1.0.6.dist-info/top_level.txt
qbism-0.1.0.6.dist-info/RECORD
